LICENSE
MANIFEST.in
README.md
setup.cfg
setup.py
Firebird.egg-info/PKG-INFO
Firebird.egg-info/SOURCES.txt
Firebird.egg-info/dependency_links.txt
Firebird.egg-info/requires.txt
Firebird.egg-info/top_level.txt
firebird/__init__.py
firebird/client.py
firebird/exceptions.py
firebird/nodes.py
firebird/pagination.py
firebird/resources/__init__.py
firebird/resources/base.py
firebird/resources/numbers.py